COPYING
HACKING.rst
MANIFEST.in
Makefile
README.rst
juju-quickstart
setup.cfg
setup.py
tox.ini
juju_quickstart.egg-info/PKG-INFO
juju_quickstart.egg-info/SOURCES.txt
juju_quickstart.egg-info/dependency_links.txt
juju_quickstart.egg-info/not-zip-safe
juju_quickstart.egg-info/requires.txt
juju_quickstart.egg-info/top_level.txt
quickstart/__init__.py
quickstart/app.py
quickstart/charmstore.py
quickstart/juju.py
quickstart/jujugui.py
quickstart/jujutools.py
quickstart/maas.py
quickstart/manage.py
quickstart/netutils.py
quickstart/packaging.py
quickstart/platform_support.py
quickstart/serializers.py
quickstart/settings.py
quickstart/ssh.py
quickstart/utils.py
quickstart/watchers.py
quickstart/cli/__init__.py
quickstart/cli/base.py
quickstart/cli/forms.py
quickstart/cli/params.py
quickstart/cli/ui.py
quickstart/cli/views.py
quickstart/models/__init__.py
quickstart/models/apiinfo.py
quickstart/models/bundles.py
quickstart/models/envs.py
quickstart/models/fields.py
quickstart/models/jenv.py
quickstart/tests/__init__.py
quickstart/tests/helpers.py
quickstart/tests/test_app.py
quickstart/tests/test_charmstore.py
quickstart/tests/test_juju.py
quickstart/tests/test_jujugui.py
quickstart/tests/test_jujutools.py
quickstart/tests/test_maas.py
quickstart/tests/test_manage.py
quickstart/tests/test_netutils.py
quickstart/tests/test_platform_support.py
quickstart/tests/test_serializers.py
quickstart/tests/test_ssh.py
quickstart/tests/test_utils.py
quickstart/tests/test_watchers.py
quickstart/tests/cli/__init__.py
quickstart/tests/cli/helpers.py
quickstart/tests/cli/test_base.py
quickstart/tests/cli/test_forms.py
quickstart/tests/cli/test_params.py
quickstart/tests/cli/test_ui.py
quickstart/tests/cli/test_views.py
quickstart/tests/functional/__init__.py
quickstart/tests/functional/test_functional.py
quickstart/tests/models/__init__.py
quickstart/tests/models/test_apiinfo.py
quickstart/tests/models/test_bundles.py
quickstart/tests/models/test_envs.py
quickstart/tests/models/test_fields.py
quickstart/tests/models/test_jenv.py