Metadata-Version: 1.1
Name: juju-quickstart
Version: 2.2.4
Summary: Juju Quickstart is a Juju plugin which allows for easily setting up a Juju
